hm/__init__.py
hm/phonemes.py
hm-0.0.3.dist-info/LICENSE
hm-0.0.3.dist-info/METADATA
hm-0.0.3.dist-info/WHEEL
hm-0.0.3.dist-info/top_level.txt
hm-0.0.3.dist-info/RECORD
