Metadata-Version: 2.1
Name: hm
Version: 0.0.3
Summary: Mnemonic tools
Home-page: https://github.com/thorwhalen/hm
Author: Thor Whalen
License: apache-2.0
Platform: any
License-File: LICENSE
